Welcome.py
WelcomeDemo2-0.0.1.dist-info/METADATA
WelcomeDemo2-0.0.1.dist-info/WHEEL
WelcomeDemo2-0.0.1.dist-info/top_level.txt
WelcomeDemo2-0.0.1.dist-info/RECORD
