Metadata-Version: 2.1
Name: WelcomeDemo2
Version: 0.0.1
Summary: Write/Read files
Home-page: UNKNOWN
Author: Dalitso Banda
Author-email: UNKNOWN
License: UNKNOWN
Platform: UNKNOWN
